Logback130Alpha4ZhongwenWendang/README.md
Logback130Alpha4ZhongwenWendang/__init__.py
Logback130Alpha4ZhongwenWendang/__main__.py
Logback130Alpha4ZhongwenWendang/file.epub
Logback130Alpha4ZhongwenWendang/index.html
Logback130Alpha4ZhongwenWendang/css/__init__.py
Logback130Alpha4ZhongwenWendang/css/annotations.css
Logback130Alpha4ZhongwenWendang/css/main.css
Logback130Alpha4ZhongwenWendang/css/normalize.css
Logback130Alpha4ZhongwenWendang/css/popup.css
Logback130Alpha4ZhongwenWendang/font/__init__.py
Logback130Alpha4ZhongwenWendang/font/fontello.eot
Logback130Alpha4ZhongwenWendang/font/fontello.svg
Logback130Alpha4ZhongwenWendang/font/fontello.ttf
Logback130Alpha4ZhongwenWendang/font/fontello.woff
Logback130Alpha4ZhongwenWendang/img/__init__.py
Logback130Alpha4ZhongwenWendang/img/annotator-glyph-sprite.png
Logback130Alpha4ZhongwenWendang/img/annotator-icon-sprite.png
Logback130Alpha4ZhongwenWendang/img/apple-touch-icon.png
Logback130Alpha4ZhongwenWendang/img/cancelfullscreen.png
Logback130Alpha4ZhongwenWendang/img/close.png
Logback130Alpha4ZhongwenWendang/img/fullscreen.png
Logback130Alpha4ZhongwenWendang/img/loader.gif
Logback130Alpha4ZhongwenWendang/img/menu-icon.png
Logback130Alpha4ZhongwenWendang/img/save.png
Logback130Alpha4ZhongwenWendang/img/saved.png
Logback130Alpha4ZhongwenWendang/img/settings-s.png
Logback130Alpha4ZhongwenWendang/img/settings.png
Logback130Alpha4ZhongwenWendang/img/star.png
Logback130Alpha4ZhongwenWendang/js/__init__.py
Logback130Alpha4ZhongwenWendang/js/epub.js
Logback130Alpha4ZhongwenWendang/js/epub.min.js
Logback130Alpha4ZhongwenWendang/js/epub.min.map
Logback130Alpha4ZhongwenWendang/js/hooks.min.js
Logback130Alpha4ZhongwenWendang/js/hooks.min.map
Logback130Alpha4ZhongwenWendang/js/reader.js
Logback130Alpha4ZhongwenWendang/js/reader.js.map
Logback130Alpha4ZhongwenWendang/js/reader.min.js
Logback130Alpha4ZhongwenWendang/js/reader.min.map
Logback130Alpha4ZhongwenWendang/js/hooks/__init__.py
logback_1_3_0_alpha4_zhongwen_wendang-2024.3.5.0.dist-info/METADATA
logback_1_3_0_alpha4_zhongwen_wendang-2024.3.5.0.dist-info/WHEEL
logback_1_3_0_alpha4_zhongwen_wendang-2024.3.5.0.dist-info/entry_points.txt
logback_1_3_0_alpha4_zhongwen_wendang-2024.3.5.0.dist-info/top_level.txt
logback_1_3_0_alpha4_zhongwen_wendang-2024.3.5.0.dist-info/RECORD
